{
   "abstract" : "Ensure that a platform has weaken support",
   "author" : [
      "Adam Kennedy <adamk@cpan.org>"
   ],
   "dynamic_config" : 0,
   "generated_by" : "Module::Install version 1.00, CPAN::Meta::Converter version 2.143240",
   "license" : [
      "perl_5"
   ],
   "meta-spec" : {
      "url" : "http://search.cpan.org/perldoc?CPAN::Meta::Spec",
      "version" : "2"
   },
   "name" : "Task-Weaken",
   "no_index" : {
      "directory" : [
         "inc",
         "t",
         "xt"
      ]
   },
   "prereqs" : {
      "build" : {
         "requires" : {
            "ExtUtils::MakeMaker" : "6.42",
            "File::Spec" : "0.80",
            "Test::More" : "0.42"
         }
      },
      "configure" : {
         "requires" : {
            "ExtUtils::MakeMaker" : "0"
         }
      },
      "runtime" : {
         "requires" : {
            "Scalar::Util" : "1.14",
            "perl" : "5.005"
         }
      }
   },
   "release_status" : "stable",
   "resources" : {
      "license" : [
         "http://dev.perl.org/licenses/"
      ],
      "repository" : {
         "url" : "http://svn.ali.as/cpan/trunk/Task-Weaken"
      },
      "x_ChangeLog" : "http://fisheye2.atlassian.com/changelog/cpan/trunk/Task-Weaken"
   },
   "version" : "1.04",
   "x_module_name" : "Task::Weaken"
}
